abrechnung/__init__.py
abrechnung/__main__.py
abrechnung/admin.py
abrechnung/config.py
abrechnung/demo.py
abrechnung/mailer.py
abrechnung/subcommand.py
abrechnung/util.py
abrechnung/application/__init__.py
abrechnung/application/accounts.py
abrechnung/application/groups.py
abrechnung/application/transactions.py
abrechnung/application/users.py
abrechnung/database/__init__.py
abrechnung/database/revisions/0001_initial_schema.sql
abrechnung/database/revisions/0002_subscriptions.sql
abrechnung/database/revisions/0003_purchase_items.sql
abrechnung/database/revisions/0004_relax_db_constraints.sql
abrechnung/database/revisions/0005_partial_data_fetching.sql
abrechnung/database/revisions/0006_fix_foreign_key_constraints.sql
abrechnung/database/revisions/0007_invite_join_as_editor.sql
abrechnung/database/revisions/0008_file_upload.sql
abrechnung/database/revisions/0009_robust_notifications.sql
abrechnung/database/revisions/0010_clearing_accounts.sql
abrechnung/database/revisions/0011_cascade_fixes.sql
abrechnung/database/revisions/0012_correct_change_dates.sql
abrechnung/database/revisions/0013_register_with_invite.sql
abrechnung/database/revisions/0014_associate_accounts_with_users.sql
abrechnung/database/revisions/__init__.py
abrechnung/domain/__init__.py
abrechnung/domain/accounts.py
abrechnung/domain/groups.py
abrechnung/domain/transactions.py
abrechnung/domain/users.py
abrechnung/http/__init__.py
abrechnung/http/accounts.py
abrechnung/http/auth.py
abrechnung/http/groups.py
abrechnung/http/serializers.py
abrechnung/http/transactions.py
abrechnung/http/utils.py
abrechnung/http/websocket.py
abrechnung/http/openapi/__init__.py
abrechnung/http/openapi/middlewares.py
abrechnung/http/openapi/openapi.py
abrechnung/http/openapi/setup.py
abrechnung/http/openapi/utils.py
abrechnung/http/openapi/decorators/__init__.py
abrechnung/http/openapi/decorators/docs.py
abrechnung/http/openapi/decorators/request.py
abrechnung/http/openapi/decorators/response.py
abrechnung-0.9.0.dist-info/entry_points.txt
abrechnung-0.9.0.dist-info/COPYING
abrechnung-0.9.0.dist-info/LICENSE
abrechnung-0.9.0.dist-info/WHEEL
abrechnung-0.9.0.dist-info/METADATA
abrechnung-0.9.0.dist-info/RECORD
