Metadata-Version: 2.1
Name: abrechnung
Version: 0.9.0
Summary: Abrechnung - feature complete payment management and bookkeeping.
Author-email: Michael Loipführer <milo@sft.lol>, Jonas Jelten <jj@sft.lol>, Michael Enßlin <mic@sft.lol>
Requires-Python: >=3.9
Classifier: Operating System :: OS Independent
Classifier: Programming Language :: Python :: 3
Classifier: License :: OSI Approved :: GNU General Public License v3 (GPLv3)
Classifier: Development Status :: 5 - Production/Stable
Requires-Dist: aiohttp~=3.8
Requires-Dist: aiohttp-cors~=0.7
Requires-Dist: asyncpg~=0.24
Requires-Dist: bcrypt~=3.2
Requires-Dist: pyjwt~=2.2
Requires-Dist: PyYAML~=5.3
Requires-Dist: marshmallow~=3.14
Requires-Dist: schema
Requires-Dist: email-validator~=1.1
Requires-Dist: apispec
Requires-Dist: webargs
Requires-Dist: black ; extra == "dev"
Requires-Dist: mypy~=0.930 ; extra == "dev"
Requires-Dist: types-PyYAML~=5.4 ; extra == "dev"
Requires-Dist: pylint~=2.12 ; extra == "dev"
Requires-Dist: sphinx ; extra == "docs"
Requires-Dist: sphinx-autobuild ; extra == "docs"
Requires-Dist: sphinx-autodoc-typehints ; extra == "docs"
Requires-Dist: aiosmtpd~=1.4 ; extra == "test"
Requires-Dist: pytest ; extra == "test"
Requires-Dist: pytest-cov ; extra == "test"
Project-URL: Documentation, https://abrechnung.readthedocs.io
Project-URL: Source, https://github.com/SFTtech/abrechung
Provides-Extra: dev
Provides-Extra: docs
Provides-Extra: test
